fastfuels_sdk/__init__.py
fastfuels_sdk/api.py
fastfuels_sdk/convenience.py
fastfuels_sdk/domains.py
fastfuels_sdk/exceptions.py
fastfuels_sdk/exports.py
fastfuels_sdk/features.py
fastfuels_sdk/inventories.py
fastfuels_sdk/pointclouds.py
fastfuels_sdk/utils.py
fastfuels_sdk/client_library/__init__.py
fastfuels_sdk/client_library/api_client.py
fastfuels_sdk/client_library/api_response.py
fastfuels_sdk/client_library/configuration.py
fastfuels_sdk/client_library/exceptions.py
fastfuels_sdk/client_library/py.typed
fastfuels_sdk/client_library/rest.py
fastfuels_sdk/client_library/api/__init__.py
fastfuels_sdk/client_library/api/als_point_cloud_api.py
fastfuels_sdk/client_library/api/api_keys_api.py
fastfuels_sdk/client_library/api/applications_api.py
fastfuels_sdk/client_library/api/cookies_api.py
fastfuels_sdk/client_library/api/domains_api.py
fastfuels_sdk/client_library/api/feature_grid_api.py
fastfuels_sdk/client_library/api/features_api.py
fastfuels_sdk/client_library/api/grids_api.py
fastfuels_sdk/client_library/api/index_api.py
fastfuels_sdk/client_library/api/inventories_api.py
fastfuels_sdk/client_library/api/point_cloud_api.py
fastfuels_sdk/client_library/api/road_feature_api.py
fastfuels_sdk/client_library/api/surface_grid_api.py
fastfuels_sdk/client_library/api/topography_grid_api.py
fastfuels_sdk/client_library/api/tree_grid_api.py
fastfuels_sdk/client_library/api/tree_inventory_api.py
fastfuels_sdk/client_library/api/water_feature_api.py
fastfuels_sdk/client_library/models/__init__.py
fastfuels_sdk/client_library/models/access.py
fastfuels_sdk/client_library/models/als_point_cloud.py
fastfuels_sdk/client_library/models/als_point_cloud_source.py
fastfuels_sdk/client_library/models/api_resources_inventories_tree_schema_processing_error.py
fastfuels_sdk/client_library/models/api_resources_inventories_tree_schema_upload_response.py
fastfuels_sdk/client_library/models/api_resources_pointclouds_als_schema_upload_response.py
fastfuels_sdk-0.18.0.dist-info/licenses/LICENSE
fastfuels_sdk-0.18.0.dist-info/METADATA
fastfuels_sdk-0.18.0.dist-info/WHEEL
fastfuels_sdk-0.18.0.dist-info/top_level.txt
fastfuels_sdk-0.18.0.dist-info/RECORD
