Metadata-Version: 2.4
Name: fastfuels-sdk
Version: 0.18.0
Summary: 3D Fuels for Next Generation Fire Models
Home-page: https://github.com/silvxlabs/fastfuels-sdk-python
License: MIT
Project-URL: Bug Tracker, https://github.com/silvxlabs/fastfuels-sdk-python/issues
Classifier: Intended Audience :: Developers
Classifier: Intended Audience :: Science/Research
Classifier: License :: OSI Approved :: MIT License
Classifier: Operating System :: OS Independent
Classifier: Programming Language :: Python :: 3
Classifier: Programming Language :: Python :: 3.9
Classifier: Programming Language :: Python :: 3.10
Classifier: Programming Language :: Python :: 3.11
Classifier: Programming Language :: Python :: 3.12
Classifier: Programming Language :: Python :: 3.13
Classifier: Topic :: Scientific/Engineering
Requires-Python: >=3.9
License-File: LICENSE
Requires-Dist: geopandas
Requires-Dist: numpy
Requires-Dist: pandas
Requires-Dist: pydantic>=2
Requires-Dist: requests
Requires-Dist: scipy
Requires-Dist: urllib3>=2.1.0
Requires-Dist: zarr
Dynamic: classifier
Dynamic: description
Dynamic: description-content-type
Dynamic: home-page
Dynamic: license
Dynamic: license-file
Dynamic: project-url
Dynamic: requires-dist
Dynamic: requires-python
Dynamic: summary
